zebra_analyzer/__init__.py
zebra_analyzer/analyzer.py
zebra_analyzer/utils.py
zebra_analyzer/zebra_files/ZEBRA.D
zebra_analyzer/zebra_files/ZEBRA.DP
zebra_analyzer/zebra_files/ZEBRA.SAS
zebra_analyzer/zebra_files/ZEBRA.exe
zebra_analyzer/zebra_files/Zebra_Prop_Liq.txt
zebra_analyzer/zebra_files/Zebra_Prop_Sat.txt
zebra_analyzer/zebra_files/Zebra_Prop_out.txt
zebra_analyzer/zebra_files/zebra.in
zebra_analyzer-0.1.dist-info/METADATA
zebra_analyzer-0.1.dist-info/WHEEL
zebra_analyzer-0.1.dist-info/entry_points.txt
zebra_analyzer-0.1.dist-info/top_level.txt
zebra_analyzer-0.1.dist-info/RECORD
