Metadata-Version: 2.4
Name: zebra_analyzer
Version: 0.1
Summary: Zebra Simulation Analyzer Library
Home-page: https://github.com/alisiraydemir/zebra_analyzer
Author: Senin Adın
Classifier: Programming Language :: Python :: 3
Classifier: License :: OSI Approved :: MIT License
Requires-Dist: pandas
Requires-Dist: matplotlib
Requires-Dist: adjustText
Dynamic: author
Dynamic: classifier
Dynamic: description-content-type
Dynamic: home-page
Dynamic: requires-dist
Dynamic: summary
